README.rst
setup.py
bin/findltr
findltr/__init__.py
findltr/_version.py
findltr/algorithms.py
findltr/grouping.py
findltr/utils.py
findltr.egg-info/PKG-INFO
findltr.egg-info/SOURCES.txt
findltr.egg-info/dependency_links.txt
findltr.egg-info/not-zip-safe
findltr.egg-info/requires.txt
findltr.egg-info/top_level.txt