Metadata-Version: 1.1
Name: findltr
Version: 0.0.1
Summary: Get membership details from various data sources.
Home-page: https://github.com/maybelinot/findltr
Author: Eduard Trott
Author-email: etrott@redhat.com
License: GPLv2
Download-URL: https://github.com/maybelinot/findltr/archive/master.zip
Keywords: information
Platform: UNKNOWN
Classifier: License :: OSI Approved :: GNU General Public License v3 (GPLv3)
Classifier: Natural Language :: English
Classifier: Programming Language :: Python :: 2.7
Classifier: Topic :: Office/Business
Classifier: Topic :: Utilities
Provides: findltr
